{
    "data": [
        {
            "Accumulated": 1075,
            "Date": "2026-05-01",
            "Number of Words": 1075
        },
        {
            "Accumulated": 2461,
            "Date": "2026-05-02",
            "Number of Words": 1386
        },
        {
            "Accumulated": 3351,
            "Date": "2026-05-03",
            "Number of Words": 890
        },
        {
            "Accumulated": 3528,
            "Date": "2026-05-04",
            "Number of Words": 177
        },
        {
            "Accumulated": 4874,
            "Date": "2026-05-05",
            "Number of Words": 1346
        },
        {
            "Accumulated": 5244,
            "Date": "2026-05-06",
            "Number of Words": 370
        },
        {
            "Accumulated": 6049,
            "Date": "2026-05-07",
            "Number of Words": 805
        },
        {
            "Accumulated": 6881,
            "Date": "2026-05-08",
            "Number of Words": 832
        },
        {
            "Accumulated": 8016,
            "Date": "2026-05-09",
            "Number of Words": 1135
        },
        {
            "Accumulated": 8305,
            "Date": "2026-05-10",
            "Number of Words": 289
        },
        {
            "Accumulated": 9284,
            "Date": "2026-05-11",
            "Number of Words": 979
        },
        {
            "Accumulated": 10142,
            "Date": "2026-05-12",
            "Number of Words": 858
        },
        {
            "Accumulated": 10354,
            "Date": "2026-05-13",
            "Number of Words": 212
        },
        {
            "Accumulated": 11938,
            "Date": "2026-05-14",
            "Number of Words": 1584
        },
        {
            "Accumulated": 12321,
            "Date": "2026-05-15",
            "Number of Words": 383
        },
        {
            "Accumulated": 12732,
            "Date": "2026-05-16",
            "Number of Words": 411
        },
        {
            "Accumulated": 13101,
            "Date": "2026-05-17",
            "Number of Words": 369
        },
        {
            "Accumulated": 13101,
            "Date": "2026-05-18",
            "Number of Words": 0
        },
        {
            "Accumulated": 14300,
            "Date": "2026-05-19",
            "Number of Words": 1199
        },
        {
            "Accumulated": 14727,
            "Date": "2026-05-20",
            "Number of Words": 427
        },
        {
            "Accumulated": 14924,
            "Date": "2026-05-21",
            "Number of Words": 197
        },
        {
            "Accumulated": 15530,
            "Date": "2026-05-22",
            "Number of Words": 606
        },
        {
            "Accumulated": 16030,
            "Date": "2026-05-23",
            "Number of Words": 500
        },
        {
            "Accumulated": 16707,
            "Date": "2026-05-24",
            "Number of Words": 677
        },
        {
            "Accumulated": 17567,
            "Date": "2026-05-25",
            "Number of Words": 860
        },
        {
            "Accumulated": 19348,
            "Date": "2026-05-26",
            "Number of Words": 1781
        },
        {
            "Accumulated": 21160,
            "Date": "2026-05-27",
            "Number of Words": 1812
        },
        {
            "Accumulated": 23262,
            "Date": "2026-05-28",
            "Number of Words": 2102
        },
        {
            "Accumulated": 26769,
            "Date": "2026-05-29",
            "Number of Words": 3507
        },
        {
            "Accumulated": 29459,
            "Date": "2026-05-30",
            "Number of Words": 2690
        },
        {
            "Accumulated": 30682,
            "Date": "2026-05-31",
            "Number of Words": 1223
        }
    ]
}